streaming_sql_engine/README.md
streaming_sql_engine/__init__.py
streaming_sql_engine/engine.py
streaming_sql_engine/requirements.txt
streaming_sql_engine/core/__init__.py
streaming_sql_engine/core/evaluator.py
streaming_sql_engine/core/executor.py
streaming_sql_engine/core/optimizer.py
streaming_sql_engine/core/parser.py
streaming_sql_engine/core/planner.py
streaming_sql_engine/operators/__init__.py
streaming_sql_engine/operators/base.py
streaming_sql_engine/operators/mmap.py
streaming_sql_engine/operators/polars.py
streaming_sql_engine/polars_utils/__init__.py
streaming_sql_engine/polars_utils/operators.py
streaming_sql_engine/polars_utils/translator.py
streaming_sql_engine/storage/__init__.py
streaming_sql_engine/storage/mmap_index.py
streaming_sql_engine-0.1.31.dist-info/METADATA
streaming_sql_engine-0.1.31.dist-info/WHEEL
streaming_sql_engine-0.1.31.dist-info/top_level.txt
streaming_sql_engine-0.1.31.dist-info/RECORD
