Metadata-Version: 2.4
Name: streaming-sql-engine
Version: 0.1.31
Summary: Streaming SQL Engine: Lightweight Cross Data Source Integration for Resource Constraint Environments
Author-email: Ierofantis <teopanta1986@gmail.com>
Project-URL: Homepage, https://github.com/Ierofantis/streaming_sql_engine/
Project-URL: Repository, https://github.com/Ierofantis/streaming_sql_engine/
Project-URL: Issues, https://github.com/Ierofantis/streaming_sql_engine/issues
Project-URL: Documentation, https://github.com/Ierofantis/streaming_sql_engine/blob/master/README.md
Project-URL: Scientific-Paper, https://github.com/Ierofantis/streaming_sql_engine/blob/master/Streaming_SQL_Engine_Paper.pdf
Keywords: sql,streaming,join,database,query,engine,etl,data-integration
Classifier: Development Status :: 3 - Alpha
Classifier: Intended Audience :: Developers
Classifier: Topic :: Software Development :: Libraries :: Python Modules
Classifier: Topic :: Database
Classifier: License :: OSI Approved :: MIT License
Classifier: Programming Language :: Python :: 3
Classifier: Programming Language :: Python :: 3.8
Classifier: Programming Language :: Python :: 3.9
Classifier: Programming Language :: Python :: 3.10
Classifier: Programming Language :: Python :: 3.11
Classifier: Programming Language :: Python :: 3.12
Requires-Python: >=3.8
Requires-Dist: sqlglot>=23.0.0
Requires-Dist: polars>=0.19.0
Provides-Extra: db
Requires-Dist: psycopg2-binary>=2.9.0; extra == "db"
Requires-Dist: pymysql>=1.0.0; extra == "db"
Requires-Dist: DBUtils>=3.0.0; extra == "db"
Requires-Dist: pymongo>=4.0.0; extra == "db"
Provides-Extra: dev
Requires-Dist: pytest>=7.0.0; extra == "dev"
Requires-Dist: pytest-cov>=4.0.0; extra == "dev"
Requires-Dist: black>=23.0.0; extra == "dev"
Requires-Dist: flake8>=6.0.0; extra == "dev"
Provides-Extra: all
Requires-Dist: psycopg2-binary>=2.9.0; extra == "all"
Requires-Dist: pymysql>=1.0.0; extra == "all"
Requires-Dist: DBUtils>=3.0.0; extra == "all"
Requires-Dist: pymongo>=4.0.0; extra == "all"
